apls/__init__.py
apls/apls.py
apls/apls_plots.py
apls/apls_utils.py
apls/create_spacenet_masks.py
apls/graphTools.py
apls/osmnx_funcs.py
apls/road_speed.py
apls/sp_metric.py
apls/topo_metric.py
apls/wkt_to_G.py
apls/data/__init__.py
apls-0.1.0.dist-info/LICENSE.txt
apls-0.1.0.dist-info/METADATA
apls-0.1.0.dist-info/WHEEL
apls-0.1.0.dist-info/top_level.txt
apls-0.1.0.dist-info/RECORD
