Metadata-Version: 2.1
Name: apls
Version: 0.1.0
Summary: CosmiQ Works APLS Metric Implementation
Home-page: https://github.com/CosmiQ/apls
Author: Adam Van Etten
Author-email: avanetten@iqt.org
License: Apache-2.0
Keywords: spacenet machinelearning iou aws
Platform: UNKNOWN
Classifier: Intended Audience :: Information Technology
Classifier: Intended Audience :: Science/Research
Classifier: License :: OSI Approved :: BSD License
Classifier: Programming Language :: Python :: 3.6
Classifier: Topic :: Scientific/Engineering :: GIS
Requires-Dist: matplotlib (>=3.0.0)
Requires-Dist: shapely (>=1.6.4)
Requires-Dist: pandas (>=0.23.4)
Requires-Dist: geopandas (>=0.4.0)
Requires-Dist: opencv-python (>=4.0)
Requires-Dist: numpy (>=1.15.4)
Requires-Dist: tqdm (>=4.28.1)
Requires-Dist: GDAL (==2.4.0)
Requires-Dist: rtree (>=0.8.3)
Requires-Dist: networkx (>=2.2)
Requires-Dist: scipy (>=1.2.0)
Requires-Dist: scikit-image (>=0.14.0)
Requires-Dist: affine (>=2.2.1)
Requires-Dist: utm (>=0.4.0)
Provides-Extra: test
Requires-Dist: mock ; extra == 'test'
Requires-Dist: pytest ; extra == 'test'
Requires-Dist: pytest-cov ; extra == 'test'
Requires-Dist: codecov ; extra == 'test'
